nn_pruning/__init__.py
nn_pruning/hp_naming.py
nn_pruning/inference_model_patcher.py
nn_pruning/model_patcher.py
nn_pruning/model_structure.py
nn_pruning/patch_coordinator.py
nn_pruning/sparse_trainer.py
nn_pruning/sparse_xp.py
nn_pruning/training_patcher.py
nn_pruning/modules/binarizer.py
nn_pruning/modules/gelu2relu.py
nn_pruning/modules/masked_nn.py
nn_pruning/modules/nonorm.py
nn_pruning-0.1.2.dist-info/LICENSE
nn_pruning-0.1.2.dist-info/METADATA
nn_pruning-0.1.2.dist-info/WHEEL
nn_pruning-0.1.2.dist-info/entry_points.txt
nn_pruning-0.1.2.dist-info/top_level.txt
nn_pruning-0.1.2.dist-info/RECORD
